gayson
