Metadata-Version: 1.1
Name: hackwork-gayson
Version: 0.0.3
Summary: A software package to help with persisting to and reading from DB for more Python objects
Home-page: https://serioese.gmbh/
Author: Simon Welker
Author-email: simon@serioese.gmbh
License: MIT License
Platform: UNKNOWN
Classifier: Environment :: Web Environment
Classifier: Intended Audience :: Developers
Classifier: License :: OSI Approved :: MIT License
Classifier: Operating System :: OS Independent
Classifier: Programming Language :: Python :: 3.7
Classifier: Topic :: Internet :: WWW/HTTP
Classifier: Topic :: Internet :: WWW/HTTP :: Dynamic Content
